MANIFEST.in
README.rst
setup.py
twyg/__init__.py
twyg/cairowrapper.py
twyg/cmdline.py
twyg/colorizer.py
twyg/common.py
twyg/config.py
twyg/connection.py
twyg/css3colors.py
twyg/geom.py
twyg/geomutils.py
twyg/hyphenator.py
twyg/layout.py
twyg/node.py
twyg/ordereddict.py
twyg/textwrap.py
twyg/tree.py
twyg.egg-info/PKG-INFO
twyg.egg-info/SOURCES.txt
twyg.egg-info/dependency_links.txt
twyg.egg-info/entry_points.txt
twyg.egg-info/not-zip-safe
twyg.egg-info/top_level.txt
twyg/colors/aqua.twg
twyg/colors/azure.twg
twyg/colors/bordeaux.twg
twyg/colors/clay.twg
twyg/colors/cmyk.twg
twyg/colors/cobalt.twg
twyg/colors/colors21.twg
twyg/colors/crayons.twg
twyg/colors/earth.twg
twyg/colors/forest.twg
twyg/colors/grape.twg
twyg/colors/honey.twg
twyg/colors/inca.twg
twyg/colors/jelly.twg
twyg/colors/kelp.twg
twyg/colors/mango.twg
twyg/colors/mellow.twg
twyg/colors/merlot.twg
twyg/colors/milkshake.twg
twyg/colors/mint-gray.twg
twyg/colors/mint.twg
twyg/colors/moon.twg
twyg/colors/mustard.twg
twyg/colors/neo.twg
twyg/colors/orbit.twg
twyg/colors/pastels.twg
twyg/colors/quartz.twg
twyg/colors/salmon.twg
twyg/colors/tentacle.twg
twyg/colors/terracotta.twg
twyg/colors/turquoise.twg
twyg/colors/violet.twg
twyg/configs/boxes.twg
twyg/configs/bubbles.twg
twyg/configs/default.twg
twyg/configs/edge.twg
twyg/configs/flowchart.twg
twyg/configs/hive.twg
twyg/configs/ios.twg
twyg/configs/jellyfish.twg
twyg/configs/junction1.twg
twyg/configs/junction2.twg
twyg/configs/lines.twg
twyg/configs/modern.twg
twyg/configs/nazca.twg
twyg/configs/rounded.twg
twyg/configs/square.twg
twyg/configs/synapse-connection.twg
twyg/configs/synapse.twg
twyg/configs/tron.twg
twyg/defaults/level.twg
twyg/defaults/colorizer/branch.twg
twyg/defaults/colorizer/colorscheme.twg
twyg/defaults/colorizer/common.twg
twyg/defaults/colorizer/cycle.twg
twyg/defaults/colorizer/depth.twg
twyg/defaults/connection/curve.twg
twyg/defaults/connection/junction.twg
twyg/defaults/layout/layout.twg
twyg/defaults/node/box.twg
twyg/defaults/node/common.twg
twyg/defaults/node/line.twg
twyg/defaults/node/oval.twg
twyg/defaults/node/poly.twg
twyg/defaults/node/rect.twg